metricsoperator/__init__.py
metricsoperator/client.py
metricsoperator/utils.py
metricsoperator/metrics/__init__.py
metricsoperator/metrics/base.py
metricsoperator/metrics/perf.py
metricsoperator/metrics/storage.py
metricsoperator/metrics/app/__init__.py
metricsoperator/metrics/app/amg.py
metricsoperator/metrics/app/lammps.py
metricsoperator/metrics/network/__init__.py
metricsoperator/metrics/network/netmark.py
metricsoperator/metrics/network/osu_benchmark.py
metricsoperator-0.1.11.dist-info/METADATA
metricsoperator-0.1.11.dist-info/WHEEL
metricsoperator-0.1.11.dist-info/top_level.txt
metricsoperator-0.1.11.dist-info/RECORD
