Metadata-Version: 2.1
Name: metricsoperator
Version: 0.1.11
Summary: Python helpers for the Metrics Operator
Home-page: https://github.com/converged-computing/metrics-operator/tree/main/python-sdk/v1alpha2
Author: Vanessasaurus
Author-email: vsoch@users.noreply.github.com
Maintainer: Vanessasaurus
License: MIT
Keywords: metrics-operator,hpc,kubernetes,metrics,storage,applications
Classifier: Intended Audience :: Science/Research
Classifier: Intended Audience :: Developers
Classifier: License :: OSI Approved :: Apache Software License
Classifier: Programming Language :: C
Classifier: Programming Language :: Python
Classifier: Topic :: Software Development
Classifier: Topic :: Scientific/Engineering
Classifier: Operating System :: Unix
Classifier: Programming Language :: Python :: 3.7
Requires-Dist: kubernetes
Requires-Dist: requests
Requires-Dist: pyyaml
